garpix_jira/MANIFEST.in
garpix_jira/__init__.py
garpix_jira/apps.py
garpix_jira/setup.py
garpix_jira/__pycache__/__init__.cpython-38.pyc
garpix_jira/__pycache__/apps.cpython-38.pyc
garpix_jira/admin/__init__.py
garpix_jira/admin/issue.py
garpix_jira/admin/plan_estimate.py
garpix_jira/admin/project.py
garpix_jira/admin/project_category.py
garpix_jira/admin/project_document.py
garpix_jira/admin/server.py
garpix_jira/admin/specialization.py
garpix_jira/admin/user.py
garpix_jira/admin/worklog.py
garpix_jira/admin/__pycache__/__init__.cpython-38.pyc
garpix_jira/admin/__pycache__/issue.cpython-38.pyc
garpix_jira/admin/__pycache__/plan_estimate.cpython-38.pyc
garpix_jira/admin/__pycache__/project.cpython-38.pyc
garpix_jira/admin/__pycache__/project_category.cpython-38.pyc
garpix_jira/admin/__pycache__/project_document.cpython-38.pyc
garpix_jira/admin/__pycache__/server.cpython-38.pyc
garpix_jira/admin/__pycache__/specialization.cpython-38.pyc
garpix_jira/admin/__pycache__/user.cpython-38.pyc
garpix_jira/admin/__pycache__/worklog.cpython-38.pyc
garpix_jira/management/commands/jira_sync_all.py
garpix_jira/management/commands/__pycache__/jira_sync_all.cpython-38.pyc
garpix_jira/models/__init__.py
garpix_jira/models/issue.py
garpix_jira/models/plan_estimate.py
garpix_jira/models/project.py
garpix_jira/models/project_category.py
garpix_jira/models/project_document.py
garpix_jira/models/server.py
garpix_jira/models/specialization.py
garpix_jira/models/user.py
garpix_jira/models/worklog.py
garpix_jira/models/__pycache__/__init__.cpython-38.pyc
garpix_jira/models/__pycache__/issue.cpython-38.pyc
garpix_jira/models/__pycache__/plan_estimate.cpython-38.pyc
garpix_jira/models/__pycache__/project.cpython-38.pyc
garpix_jira/models/__pycache__/project_category.cpython-38.pyc
garpix_jira/models/__pycache__/project_document.cpython-38.pyc
garpix_jira/models/__pycache__/server.cpython-38.pyc
garpix_jira/models/__pycache__/specialization.cpython-38.pyc
garpix_jira-1.7.0.dist-info/METADATA
garpix_jira-1.7.0.dist-info/WHEEL
garpix_jira-1.7.0.dist-info/top_level.txt
garpix_jira-1.7.0.dist-info/RECORD
